Metadata-Version: 1.1
Name: sqliteshell
Version: 0.1.0
Summary: Just-about-tolerable sqlite shell for use with in-memory sqlite.
Home-page: https://github.com/jlee_made/sqliteshell
Author: John Lee
Author-email: UNKNOWN
License: MIT
Platform: any
Classifier: Development Status :: 4 - Beta
Classifier: Intended Audience :: Developers
Classifier: License :: OSI Approved :: MIT License
Classifier: Operating System :: POSIX
Classifier: Programming Language :: Python :: 3
